jupyterlab_recents/__init__.py
jupyterlab_recents/_version.py
jupyterlab_recents-3.3.0.data/data/share/jupyter/labextensions/@jlab-enhanced/recents/package.json
jupyterlab_recents-3.3.0.data/data/share/jupyter/labextensions/@jlab-enhanced/recents/schemas/@jlab-enhanced/recents/package.json.orig
jupyterlab_recents-3.3.0.data/data/share/jupyter/labextensions/@jlab-enhanced/recents/schemas/@jlab-enhanced/recents/plugin.json
jupyterlab_recents-3.3.0.data/data/share/jupyter/labextensions/@jlab-enhanced/recents/static/868.0f2de326e88955a3f498.js
jupyterlab_recents-3.3.0.data/data/share/jupyter/labextensions/@jlab-enhanced/recents/static/remoteEntry.486a65739816aba78933.js
jupyterlab_recents-3.3.0.data/data/share/jupyter/labextensions/@jlab-enhanced/recents/static/style.js
jupyterlab_recents-3.3.0.data/data/share/jupyter/labextensions/@jlab-enhanced/recents/static/third-party-licenses.json
jupyterlab_recents-3.3.0.data/data/share/jupyter/labextensions/@jlab-enhanced/recents/install.json
jupyterlab_recents-3.3.0.dist-info/METADATA
jupyterlab_recents-3.3.0.dist-info/WHEEL
jupyterlab_recents-3.3.0.dist-info/licenses/LICENSE
jupyterlab_recents-3.3.0.dist-info/RECORD
