Metadata-Version: 2.1
Name: jupyterlab_recents
Version: 3.3.0
Summary: Track recent files and folders.
Project-URL: Homepage, https://github.com/jupyterlab-contrib/jupyterlab-recents
Project-URL: Bug Tracker, https://github.com/jupyterlab-contrib/jupyterlab-recents/issues
Project-URL: Repository, https://github.com/jupyterlab-contrib/jupyterlab-recents.git
Author: Trevor Slaton
License: Copyright (c) 2019, The Regents of the University of California, through Lawrence Berkeley National Laboratory (subject to receipt of any required approvals from the U.S. Dept. of Energy). All rights reserved.
License-File: LICENSE
Classifier: Framework :: Jupyter
Classifier: Framework :: Jupyter :: JupyterLab
Classifier: Framework :: Jupyter :: JupyterLab :: 4
Classifier: Framework :: Jupyter :: JupyterLab :: Extensions
Classifier: Framework :: Jupyter :: JupyterLab :: Extensions :: Prebuilt
Classifier: License :: OSI Approved :: BSD License
Classifier: Programming Language :: Python
Classifier: Programming Language :: Python :: 3
Classifier: Programming Language :: Python :: 3.8
Classifier: Programming Language :: Python :: 3.9
Classifier: Programming Language :: Python :: 3.10
Classifier: Programming Language :: Python :: 3.11
Requires-Python: >=3.8
